{
  "name": "⏰ Welcome to (suggestion) The Lean Canvas Timer",
  "description": "Timers set up to help you run through Th Lean Canvas with your team. Use Timers when you need to divide a large task into smaller pieces and keep within the time frame of each one. Create your own timers or use templates. You can edit this text, the main name and even suggest your own timers. The plugin also has AutoSave feature. Have fun!",
  "isMuted": false,
  "timers": [
    {
      "name": "Read the description",
      "time": {
        "minutes": 0,
        "seconds": 20
      },
      "skip": false
    },
    {
      "name": "1. Problem",
      "time": {
        "minutes": 1,
        "seconds": 30
      },
      "skip": false
    },
    {
      "name": "2. Customer segments",
      "time": {
        "minutes": 1,
        "seconds": 30
      },
      "skip": false
    },
    {
      "name": "3. Unique Value Prop.",
      "time": {
        "minutes": 1,
        "seconds": 30
      },
      "skip": false
    },
    {
      "name": "4. Solutions",
      "time": {
        "minutes": 1,
        "seconds": 30
      },
      "skip": false
    },
    {
      "name": "5. Key Metric",
      "time": {
        "minutes": 1,
        "seconds": 30
      },
      "skip": false
    },
    {
      "name": "6. Channels",
      "time": {
        "minutes": 1,
        "seconds": 30
      },
      "skip": false
    },
    {
      "name": "7. Cost structure",
      "time": {
        "minutes": 1,
        "seconds": 30
      },
      "skip": false
    },
    {
      "name": "8. Revenue streams",
      "time": {
        "minutes": 1,
        "seconds": 30
      },
      "skip": false
    },
    {
      "name": "9. Unfair advantage",
      "time": {
        "minutes": 1,
        "seconds": 30
      },
      "skip": false
    }
  ]
}
